llama_index/postprocessor/pinecone_native_rerank/__init__.py
llama_index/postprocessor/pinecone_native_rerank/base.py
llama_index_postprocessor_pinecone_native_rerank-0.2.0.dist-info/METADATA
llama_index_postprocessor_pinecone_native_rerank-0.2.0.dist-info/WHEEL
llama_index_postprocessor_pinecone_native_rerank-0.2.0.dist-info/licenses/LICENSE
llama_index_postprocessor_pinecone_native_rerank-0.2.0.dist-info/RECORD
