Metadata-Version: 2.4
Name: llama-index-postprocessor-pinecone-native-rerank
Version: 0.2.0
Summary: llama-index postprocessor reranker models from pinecone cloud service
Author-email: Jingyi Zhao <zhao.elton@gmail.com>
License-Expression: MIT
License-File: LICENSE
Requires-Python: <4.0,>=3.9
Requires-Dist: llama-index-core<0.14,>=0.13.0
Requires-Dist: pinecone
